openml_sklearn/__init__.py
openml_sklearn/__version__.py
openml_sklearn/extension.py
openml_sklearn-1.0.0a0.dist-info/METADATA
openml_sklearn-1.0.0a0.dist-info/WHEEL
openml_sklearn-1.0.0a0.dist-info/licenses/LICENSE
openml_sklearn-1.0.0a0.dist-info/RECORD
