Metadata-Version: 2.4
Name: openml-sklearn
Version: 1.0.0a0
Summary: Extensions for running scikit-learn models on OpenML tasks
Project-URL: home, https://www.openml.org/
Project-URL: source, https://github.com/openml/openml-sklearn
Project-URL: documentation, https://github.com/openml/openml-sklearn
Author: Matthias Feurer, Jan van Rijn, Arlind Kadra, Pieter Gijsbers, Neeratyoy Mallik, Sahithya Ravi, Andreas Müller, Joaquin Vanschoren , Frank Hutter
License: BSD 3-Clause License
License-File: LICENSE
Classifier: Intended Audience :: Science/Research
Classifier: License :: OSI Approved :: BSD License
Classifier: Operating System :: MacOS
Classifier: Operating System :: POSIX
Classifier: Operating System :: Unix
Classifier: Programming Language :: Python
Classifier: Programming Language :: Python :: 3
Classifier: Programming Language :: Python :: 3.8
Classifier: Programming Language :: Python :: 3.9
Classifier: Programming Language :: Python :: 3.10
Classifier: Programming Language :: Python :: 3.11
Classifier: Programming Language :: Python :: 3.12
Classifier: Programming Language :: Python :: 3.13
Classifier: Topic :: Scientific/Engineering
Requires-Python: >=3.8
Requires-Dist: openml
Requires-Dist: packaging
Requires-Dist: pandas
Requires-Dist: scikit-learn>=0.18
Provides-Extra: test
Requires-Dist: flaky; extra == 'test'
Requires-Dist: oslo-concurrency; extra == 'test'
Requires-Dist: pytest; extra == 'test'
Requires-Dist: pytest-cov; extra == 'test'
Requires-Dist: pytest-rerunfailures; extra == 'test'
Requires-Dist: pytest-timeout; extra == 'test'
Requires-Dist: pytest-xdist; extra == 'test'
